plugins
wxbot
wxbotdb
